epoch_visualizer/__init__.py
epoch_visualizer/__version__.py
epoch_visualizer/manifold/__init__.py
epoch_visualizer/manifold/mds.py
epoch_visualizer/manifold/minkowski.py
epoch_visualizer/manifold/visualizer.py
epoch_visualizer/utils/__init__.py
epoch_visualizer/utils/loader.py
epoch_visualizer/utils/misc.py
epoch_visualizer-0.1.6.dist-info/LICENSE
epoch_visualizer-0.1.6.dist-info/METADATA
epoch_visualizer-0.1.6.dist-info/WHEEL
epoch_visualizer-0.1.6.dist-info/top_level.txt
epoch_visualizer-0.1.6.dist-info/RECORD
